eas_prediction/__init__.py
eas_prediction/blade_pb2.py
eas_prediction/blade_request.py
eas_prediction/blade_tf_request.py
eas_prediction/cacheserver_endpoint.py
eas_prediction/easyrec_client_demo.py
eas_prediction/easyrec_predict_pb2.py
eas_prediction/easyrec_request.py
eas_prediction/endpoint.py
eas_prediction/exception.py
eas_prediction/gateway_endpoint.py
eas_prediction/onnx_processor_data_helper.py
eas_prediction/onnx_processor_data_pb2.py
eas_prediction/onnx_request.py
eas_prediction/predict_client.py
eas_prediction/pytorch_predict_pb2.py
eas_prediction/queue_client.py
eas_prediction/request.py
eas_prediction/string_request.py
eas_prediction/test_predict_client.py
eas_prediction/test_queue_client.py
eas_prediction/tf_request.py
eas_prediction/tf_request_pb2.py
eas_prediction/torch_request.py
eas_prediction/torchrec_predict_pb2.py
eas_prediction/torchrec_request.py
eas_prediction/vipserver_endpoint.py
eas_prediction/weighted_round_robin.py
eas_prediction/queue_types/__init__.py
eas_prediction/queue_types/queueservice_pb2.py
eas_prediction-0.34.dist-info/LICENSE.txt
eas_prediction-0.34.dist-info/METADATA
eas_prediction-0.34.dist-info/WHEEL
eas_prediction-0.34.dist-info/top_level.txt
eas_prediction-0.34.dist-info/RECORD
